[
  {
    "id": "join-selfie",
    "type": "photo",
    "date": "2026-06-17",
    "url": "media/photos/2026-06-17-cameron-sophie-selfie.jpg",
    "title": "Cameron and Sophie",
    "caption": "Cameron and Sophie shortly after joining Juno's 7."
  },
  {
    "id": "junos-marina",
    "type": "photo",
    "date": "2026-06-17",
    "url": "media/photos/2026-06-17-junos7-marina.jpg",
    "title": "Juno's 7 in the marina",
    "caption": "Juno's 7 in the marina shortly after Cameron and Sophie joined."
  },
  {
    "id": "mooring-lines",
    "type": "photo",
    "date": "2026-06-19",
    "url": "media/photos/2026-06-19-cameron-lines.jpg",
    "title": "Learning the ropes",
    "caption": "Cameron working with lines on deck."
  },
  {
    "id": "sundeck-black",
    "type": "photo",
    "date": "2026-06-20",
    "url": "media/photos/2026-06-20-sundeck-black.jpg",
    "title": "Giving the sun deck black some love",
    "caption": "Deck work with the Greek islands beyond."
  },
  {
    "id": "junos-lipsi",
    "type": "photo",
    "date": "2026-06-20",
    "url": "media/photos/2026-06-20-junos7-at-anchor.jpg",
    "title": "Juno's 7 at anchor",
    "caption": "Juno's 7 sitting quietly against the Greek coastline."
  },
  {
    "id": "cameron-jetski",
    "type": "photo",
    "date": "2026-06-21",
    "url": "media/photos/2026-06-21-cameron-jetski.jpg",
    "title": "Sophie's first jet ski day",
    "caption": "A quiet moment around the swim platform and water toys."
  },
  {
    "id": "future-house",
    "type": "photo",
    "date": "2026-06-23",
    "url": "media/photos/2026-06-23-future-house.jpg",
    "title": "My future house",
    "caption": "The hillside villa Sophie picked out from the water."
  },
  {
    "id": "nice-spot-1",
    "type": "photo",
    "date": "2026-06-27",
    "url": "media/photos/2026-06-27-nice-spot-1.jpg",
    "title": "Nice spot for today",
    "caption": "Tender and toys alongside in a peaceful anchorage."
  },
  {
    "id": "nice-spot-2",
    "type": "photo",
    "date": "2026-06-27",
    "url": "media/photos/2026-06-27-nice-spot-2.jpg",
    "title": "Green hills and clear water",
    "caption": "A sheltered bay with water toys ready on the platform."
  },
  {
    "id": "nice-spot-3",
    "type": "photo",
    "date": "2026-06-27",
    "url": "media/photos/2026-06-27-nice-spot-3.jpg",
    "title": "Sun on the water",
    "caption": "Sunlight across the anchorage from the swim platform."
  },
  {
    "id": "underway-aft-deck",
    "type": "photo",
    "date": "2026-06-30",
    "url": "media/photos/2026-06-30-underway-aft-deck.jpg",
    "title": "Underway for another 2.5 hours",
    "caption": "A quiet afternoon at sea aboard Juno's 7, with around two and a half hours remaining before the next destination."
  },
  {
    "id": "webcam-boarding",
    "type": "video",
    "date": "2026-06-17",
    "url": "media/webcam/2026-06-17-first-boarding-webcam.mp4",
    "title": "The Beginning",
    "caption": "Webcam footage showing Cameron and Sophie boarding Juno's 7 for the first time."
  },
  {
    "id": "rather-rocky",
    "type": "video",
    "date": "2026-06-21",
    "url": "media/videos/2026-06-21-rather-rocky.mp4",
    "title": "Rather rocky",
    "caption": "Cameron's late-morning video: Rather rocky."
  },
  {
    "id": "sophie-june26",
    "type": "video",
    "date": "2026-06-26",
    "url": "media/videos/2026-06-26-sophie-video.mp4",
    "title": "Sophie video",
    "caption": "Short video sent by Sophie on 26 June."
  },
  {
    "id": "sophie-june27",
    "type": "video",
    "date": "2026-06-27",
    "url": "media/videos/2026-06-27-sophie-swim-platform.mp4",
    "title": "Sophie's swim platform video",
    "caption": "Cameron and Sophie enjoying the swim platform in a calm Greek anchorage."
  },
  {
    "id": "sophie-stormy",
    "type": "video",
    "date": "2026-06-30",
    "url": "media/videos/2026-06-30-sophie-stormy.mp4",
    "title": "A little stormy today",
    "caption": "Stormier conditions later on 30 June, captured by Sophie while underway."
  }
]